fdeunlock/cli.py
fdeunlock/fdeunlock.py
fdeunlock/checker.py
fdeunlock/__main__.py
fdeunlock/vault.py
fdeunlock/__init__.py
fdeunlock/_meta.py
fdeunlock/helpers.py
fdeunlock/pxssh.py
fdeunlock-0.7.1.dist-info/RECORD
fdeunlock-0.7.1.dist-info/top_level.txt
fdeunlock-0.7.1.dist-info/entry_points.txt
fdeunlock-0.7.1.dist-info/metadata.json
fdeunlock-0.7.1.dist-info/DESCRIPTION.rst
fdeunlock-0.7.1.dist-info/WHEEL
fdeunlock-0.7.1.dist-info/METADATA
