Metadata-Version: 2.0
Name: fdeunlock
Version: 0.7.1
Summary: Check and unlock full disk encrypted systems via ssh
Home-page: https://gitlab.com/ypid/fdeunlock
Author: Robin Schneider
Author-email: ypid@riseup.net
License: AGPL-3.0
Keywords: remote boot fde headless encryption security checksum initramfs ssh cryptsetup
Platform: UNKNOWN
Classifier: Development Status :: 4 - Beta
Classifier: Environment :: Console
Classifier: Intended Audience :: System Administrators
Classifier: License :: DFSG approved
Classifier: License :: OSI Approved :: GNU Affero General Public License v3
Classifier: Natural Language :: English
Classifier: Operating System :: OS Independent
Classifier: Programming Language :: Python :: 3
Classifier: Programming Language :: Python :: 3.4
Classifier: Programming Language :: Python :: 3.5
Classifier: Programming Language :: Python :: 3.6
Classifier: Topic :: Security :: Cryptography
Classifier: Topic :: System :: Boot :: Init
Classifier: Topic :: System :: Systems Administration
Requires-Dist: paramiko
Requires-Dist: pexpect
Requires-Dist: appdirs
Requires-Dist: hexdump
Provides-Extra: test
Requires-Dist: nose; extra == 'test'
Requires-Dist: nose2; extra == 'test'
Requires-Dist: testfixtures; extra == 'test'
Requires-Dist: tox; extra == 'test'
Requires-Dist: flake8; extra == 'test'
Requires-Dist: pylint; extra == 'test'
Requires-Dist: coverage; extra == 'test'
Requires-Dist: yamllint; extra == 'test'
